cognito_token_validator/__init__.py
cognito_token_validator/validator.py
tests/__init__.py
tests/test_token_validator.py
cognito_token_validator-0.1.3.dist-info/LICENSE
cognito_token_validator-0.1.3.dist-info/METADATA
cognito_token_validator-0.1.3.dist-info/WHEEL
cognito_token_validator-0.1.3.dist-info/top_level.txt
cognito_token_validator-0.1.3.dist-info/RECORD
