Metadata-Version: 2.1
Name: cognito-token-validator
Version: 0.1.3
Summary: A package for validating AWS Cognito tokens and using them as decorators in Flask routes or standalone Python functions
Home-page: https://github.com/dhinesh03/cognito-token-validator
Author: Dhinesh Kumar Sundaram
Author-email: dhinesh.gs@gmail.com
Classifier: Programming Language :: Python :: 3
Classifier: License :: OSI Approved :: MIT License
Classifier: Operating System :: OS Independent
Requires-Python: >=3.9
License-File: LICENSE
Requires-Dist: requests
Requires-Dist: cachetools
Requires-Dist: python-jose
